milkpay/cryptopay/__init__.py
milkpay/cryptopay/__meta__.py
milkpay/cryptopay/client.py
milkpay/cryptopay/exceptions.py
milkpay/cryptopay/py.typed
milkpay/cryptopay/enums/__init__.py
milkpay/cryptopay/enums/asset.py
milkpay/cryptopay/enums/check_status.py
milkpay/cryptopay/enums/currency_type.py
milkpay/cryptopay/enums/fiat.py
milkpay/cryptopay/enums/invoice_status.py
milkpay/cryptopay/enums/paid_buttons.py
milkpay/cryptopay/enums/update_type.py
milkpay/cryptopay/methods/__init__.py
milkpay/cryptopay/methods/base.py
milkpay/cryptopay/methods/create_check.py
milkpay/cryptopay/methods/create_invoice.py
milkpay/cryptopay/methods/delete_check.py
milkpay/cryptopay/methods/delete_invoice.py
milkpay/cryptopay/methods/get_balance.py
milkpay/cryptopay/methods/get_checks.py
milkpay/cryptopay/methods/get_currencies.py
milkpay/cryptopay/methods/get_exchange_rates.py
milkpay/cryptopay/methods/get_invoices.py
milkpay/cryptopay/methods/get_me.py
milkpay/cryptopay/methods/get_stats.py
milkpay/cryptopay/methods/get_transfers.py
milkpay/cryptopay/methods/transfer.py
milkpay/cryptopay/types/__init__.py
milkpay/cryptopay/types/app_stats.py
milkpay/cryptopay/types/balance.py
milkpay/cryptopay/types/base.py
milkpay/cryptopay/types/check.py
milkpay/cryptopay/types/currency.py
milkpay/cryptopay/types/custom.py
milkpay/cryptopay/types/exchange_rate.py
milkpay/cryptopay/types/invoice.py
milkpay/cryptopay/types/profile.py
milkpay/cryptopay/types/transfer.py
milkpay/cryptopay/types/update.py
milkpay_cryptopay-1.1.2.dist-info/METADATA
milkpay_cryptopay-1.1.2.dist-info/WHEEL
milkpay_cryptopay-1.1.2.dist-info/licenses/LICENSE
milkpay_cryptopay-1.1.2.dist-info/RECORD
